{
  "pictures": [
    {
      "name": "",
      "icon": "https://s3.amazonaws.com/com.offerpop.datastore/746569/xd3MoJ.png"
    },
    {
      "name": "",
      "icon": "https://s3.amazonaws.com/com.offerpop.datastore/746569/9ux0zo.png"
    },
    {
      "name": "",
      "icon": "https://s3.amazonaws.com/com.offerpop.datastore/746569/IW_B3i.png"
    },
    {
      "name": "",
      "icon": "https://s3.amazonaws.com/com.offerpop.datastore/746569/r_jmo0.png"
    },
    {
      "name": "",
      "icon": "https://s3.amazonaws.com/com.offerpop.datastore/746569/vV4h6e.png"
    },
    {
      "name": "",
      "icon": "https://s3.amazonaws.com/com.offerpop.datastore/746569/6xxFaT.png"
    },
    {
      "name": "",
      "icon": "https://s3.amazonaws.com/com.offerpop.datastore/746569/tkx865.png"
    },
    {
      "name": "",
      "icon": "https://s3.amazonaws.com/com.offerpop.datastore/746569/0NVuUc.png"
    },
    {
      "name": "",
      "icon": "https://s3.amazonaws.com/com.offerpop.datastore/746569/rCF765.png"
    },
    {
      "name": "",
      "icon": "https://s3.amazonaws.com/com.offerpop.datastore/746569/iXzVxY.png"
    }
  ]
}